notion2alfred_snippet/__init__.py
notion2alfred_snippet/alfred.py
notion2alfred_snippet-0.0.1.dist-info/LICENSE
notion2alfred_snippet-0.0.1.dist-info/METADATA
notion2alfred_snippet-0.0.1.dist-info/WHEEL
notion2alfred_snippet-0.0.1.dist-info/top_level.txt
notion2alfred_snippet-0.0.1.dist-info/RECORD
