Metadata-Version: 2.1
Name: notion2alfred-snippet
Version: 0.0.1
Summary: Package for automation in generating alfred snippet from notion pages
Home-page: https://github.com/hoosiki/notion2alfred_snippet.git
Author: Junsang Park
Author-email: publichey@gmail.com
License: BSD
Download-URL: https://github.com/hoosiki/notion-as-db/blob/master/dist/notion2alfred_snippet-0.0.1.tar.gz
Platform: UNKNOWN
Requires-Dist: pandas
Requires-Dist: config2
Requires-Dist: notion
Requires-Dist: notion-as-db
